incant/__init__.py
incant/__main__.py
incant/cli.py
incant/config_manager.py
incant/constants.py
incant/exceptions.py
incant/incant.py
incant/incus_cli.py
incant/provisioners/__init__.py
incant/provisioners/base.py
incant/provisioners/copy_file.py
incant/provisioners/llmnr.py
incant/provisioners/script.py
incant/provisioners/ssh_server.py
incant/provisioning_manager.py
incant/reporter.py
incant/types.py
incus_incant-0.5.dist-info/LICENSE
incus_incant-0.5.dist-info/METADATA
incus_incant-0.5.dist-info/WHEEL
incus_incant-0.5.dist-info/entry_points.txt
incus_incant-0.5.dist-info/RECORD
