Metadata-Version: 2.3
Name: incus-incant
Version: 0.5
Summary: Incant — an Incus frontend for declarative development environments
License: Apache License
Keywords: incus,containers,dev-environment,cli
Author: Lucas Nussbaum
Author-email: lucas@debian.org
Requires-Python: >=3.11,<4.0
Classifier: License :: Other/Proprietary License
Classifier: Programming Language :: Python :: 3
Classifier: Programming Language :: Python :: 3.11
Classifier: Programming Language :: Python :: 3.12
Classifier: Programming Language :: Python :: 3.13
Requires-Dist: click (>=8.1.3,<9.0.0)
Requires-Dist: jinja2 (>=3.1.2,<4.0.0)
Requires-Dist: mako (>=1.1.3,<2.0.0)
Requires-Dist: pyyaml (>=6.0,<7.0)
